fast_images_loader/__init__.py
fast_images_loader/loader.py
fast_images_loader-0.1.2.dist-info/LICENSE
fast_images_loader-0.1.2.dist-info/METADATA
fast_images_loader-0.1.2.dist-info/WHEEL
fast_images_loader-0.1.2.dist-info/entry_points.txt
fast_images_loader-0.1.2.dist-info/top_level.txt
fast_images_loader-0.1.2.dist-info/RECORD
