Metadata-Version: 2.1
Name: fast_images_loader
Version: 0.1.2
Summary: A fast and asynchronous image loader
Home-page: https://github.com/vaskers5/fast_images_loader
Author: kazanplova
Author-email: danil.krokodil@mail.ru
Project-URL: Bug Tracker, https://github.com/vaskers5/fast_images_loader/issues
Project-URL: Documentation, https://github.com/vaskers5/fast_images_loader#readme
Project-URL: Source Code, https://github.com/vaskers5/fast_images_loader
Classifier: Programming Language :: Python :: 3
Classifier: License :: OSI Approved :: MIT License
Classifier: Operating System :: OS Independent
Requires-Python: >=3.6
License-File: LICENSE
Requires-Dist: aiohttp
Requires-Dist: tqdm
Requires-Dist: loguru
Requires-Dist: nest-asyncio
